{"@context":["https://www.w3.org/ns/did/v1","https://w3id.org/security/suites/jws-2020/v1"],"id":"did:web:tng-cdn.who.int:v2:trustlist-ref:-:NLD:SCA","controller":"did:web:tng-cdn.who.int:v2:trustlist-ref:-:NLD","verificationMethod":["did:web:tng-cdn.who.int:v2:trustlist:-:NLD:SCA"],"proof":{"type":"JsonWebSignature2020","created":"2026-03-07T18:01:07Z","nonce":"dUccbYX7jtNFu05PAepbhoPSLqKeVu9v","proofPurpose":"assertionMethod","verificationMethod":"did:web:raw.githubusercontent.com:WorldHealthOrganization:tng-participants-prod:main:WHO:signing:DID","jws":"eyJiNjQiOmZhbHNlLCJjcml0IjpbImI2NCJdLCJhbGciOiJFUzI1NiJ9..MEYCIQDNUEE5reJS_tCpumYt1_B4WQv-Yov3iKzqPQtc0wgMYwIhAK7j7Ew28cSWi22DHBd6B2tr4bjxzx7RnCTZXR1zR2Ur"}}