{"@context":["https://www.w3.org/ns/did/v1","https://w3id.org/security/suites/jws-2020/v1"],"id":"did:web:tng-cdn.who.int:v2:trustlist-ref:-:-:SCA","controller":"did:web:tng-cdn.who.int:v2:trustlist-ref:-:-","verificationMethod":["did:web:tng-cdn.who.int:v2:trustlist:-:-:SCA"],"proof":{"type":"JsonWebSignature2020","created":"2025-12-14T00:00:36Z","nonce":"vPPnOc99X617HOdu9ZJ1zvTFXwUR1aww","proofPurpose":"assertionMethod","verificationMethod":"did:web:raw.githubusercontent.com:WorldHealthOrganization:tng-participants-prod:main:WHO:signing:DID","jws":"eyJiNjQiOmZhbHNlLCJjcml0IjpbImI2NCJdLCJhbGciOiJFUzI1NiJ9..MEYCIQCjrxu08DGeW0zKXFhkTA2bya4j7ug97ssp2vJoHG5G2QIhANfr5A-53XCsVDLp-Jrjqv_nJ1Xd4NU9i__SFybiq0-N"}}