{"@context":["https://www.w3.org/ns/did/v1","https://w3id.org/security/suites/jws-2020/v1"],"id":"did:web:tng-cdn.who.int:v2:trustlist-ref:-:OMN:DSC","controller":"did:web:tng-cdn.who.int:v2:trustlist-ref:-:OMN","verificationMethod":["did:web:tng-cdn.who.int:v2:trustlist:-:OMN:DSC"],"proof":{"type":"JsonWebSignature2020","created":"2025-05-17T18:01:03Z","nonce":"3Sj6WKp4PGyB7t1F4v3jNb2cLVezH02f","proofPurpose":"assertionMethod","verificationMethod":"did:web:raw.githubusercontent.com:WorldHealthOrganization:tng-participants-prod:main:WHO:signing:DID","jws":"eyJiNjQiOmZhbHNlLCJjcml0IjpbImI2NCJdLCJhbGciOiJFUzI1NiJ9..MEUCIGqOcIxleslzMtye8ZovzQVSQe13CNF05RbE-6ATyO7SAiEAwT3uIh1wlMwTWENn8bzURPsP7Q66Isg3JZ0ThNgNM04"}}