{"@context":["https://www.w3.org/ns/did/v1","https://w3id.org/security/suites/jws-2020/v1"],"id":"did:web:tng-cdn.who.int:v2:trustlist-ref:-:ALB:DSC","controller":"did:web:tng-cdn.who.int:v2:trustlist-ref:-:ALB","verificationMethod":["did:web:tng-cdn.who.int:v2:trustlist:-:ALB:DSC"],"proof":{"type":"JsonWebSignature2020","created":"2025-11-30T12:01:12Z","nonce":"3ES0pu4BNqWlP0Sv4vVKHQW06vVPMnOS","proofPurpose":"assertionMethod","verificationMethod":"did:web:raw.githubusercontent.com:WorldHealthOrganization:tng-participants-prod:main:WHO:signing:DID","jws":"eyJiNjQiOmZhbHNlLCJjcml0IjpbImI2NCJdLCJhbGciOiJFUzI1NiJ9..MEQCIGiDMWq0bQWH_gBjsY-UAsX0OfUMWRwOaCWbhRsQ68IHAiBNqptzwZiYPEGjDpb49CsEy6kffRqHb_3SaOIOf_cROA"}}