{"@context":["https://www.w3.org/ns/did/v1","https://w3id.org/security/suites/jws-2020/v1"],"id":"did:web:tng-cdn.who.int:v2:trustlist-ref:DCC:SVN:DSC","controller":"did:web:tng-cdn.who.int:v2:trustlist-ref:DCC:SVN","verificationMethod":["did:web:tng-cdn.who.int:v2:trustlist:DCC:SVN:DSC"],"proof":{"type":"JsonWebSignature2020","created":"2025-11-02T00:00:41Z","nonce":"IEKA15FvbBG1e7nv6zn2JKxWLOTM8vvl","proofPurpose":"assertionMethod","verificationMethod":"did:web:raw.githubusercontent.com:WorldHealthOrganization:tng-participants-prod:main:WHO:signing:DID","jws":"eyJiNjQiOmZhbHNlLCJjcml0IjpbImI2NCJdLCJhbGciOiJFUzI1NiJ9..MEUCIQC6XrtVZ4IbIa_s4O6aRTaYmuE_lEO9afBId1V2B2lWYwIgJKiUYXGUQUxSIET3RyKxj5QKRGG-jIUUoyCe5lvShmA"}}