{"@context":["https://www.w3.org/ns/did/v1","https://w3id.org/security/suites/jws-2020/v1"],"id":"did:web:tng-cdn.who.int:v2:trustlist-ref:DCC:SVN:DSC","controller":"did:web:tng-cdn.who.int:v2:trustlist-ref:DCC:SVN","verificationMethod":["did:web:tng-cdn.who.int:v2:trustlist:DCC:SVN:DSC"],"proof":{"type":"JsonWebSignature2020","created":"2025-05-10T18:01:03Z","nonce":"YHY8x1LPYVFGY1QTwa5U3CDzE88gT0JM","proofPurpose":"assertionMethod","verificationMethod":"did:web:raw.githubusercontent.com:WorldHealthOrganization:tng-participants-prod:main:WHO:signing:DID","jws":"eyJiNjQiOmZhbHNlLCJjcml0IjpbImI2NCJdLCJhbGciOiJFUzI1NiJ9..MEYCIQDIDuTuV5onLsGcAILrUh6uJPQezyJ_NStmNSYzBoEVMwIhAIINOmlP256uY0D9u5vpGpRLBduLWkNKA6OsMy5mhRR-"}}