{"@context":["https://www.w3.org/ns/did/v1","https://w3id.org/security/suites/jws-2020/v1"],"id":"did:web:tng-cdn.who.int:v2:trustlist-ref:-:LVA:DSC","controller":"did:web:tng-cdn.who.int:v2:trustlist-ref:-:LVA","verificationMethod":["did:web:tng-cdn.who.int:v2:trustlist:-:LVA:DSC"],"proof":{"type":"JsonWebSignature2020","created":"2025-06-30T00:01:36Z","nonce":"OqktAML7pCj17NizHe3TA3nAzNBmvUGl","proofPurpose":"assertionMethod","verificationMethod":"did:web:raw.githubusercontent.com:WorldHealthOrganization:tng-participants-prod:main:WHO:signing:DID","jws":"eyJiNjQiOmZhbHNlLCJjcml0IjpbImI2NCJdLCJhbGciOiJFUzI1NiJ9..MEQCIGliSSQ65ioWFW0tKiG1uwscAZ-Ow9f4_bJmxMjfHiB1AiA6Xk1CHzTAamS3FEh8d4u_Oz0lrRevj27NBJBZ9lMDHQ"}}