{"@context":["https://www.w3.org/ns/did/v1","https://w3id.org/security/suites/jws-2020/v1"],"id":"did:web:tng-cdn.who.int:v2:trustlist-ref:DCC:TGO:DSC","controller":"did:web:tng-cdn.who.int:v2:trustlist-ref:DCC:TGO","verificationMethod":["did:web:tng-cdn.who.int:v2:trustlist:DCC:TGO:DSC"],"proof":{"type":"JsonWebSignature2020","created":"2025-08-09T06:00:35Z","nonce":"WQdDq5MNJSFb9Gj0ZU2bcNIaXrop9wAx","proofPurpose":"assertionMethod","verificationMethod":"did:web:raw.githubusercontent.com:WorldHealthOrganization:tng-participants-prod:main:WHO:signing:DID","jws":"eyJiNjQiOmZhbHNlLCJjcml0IjpbImI2NCJdLCJhbGciOiJFUzI1NiJ9..MEUCIQDR58qjLiQIZ9Poxj-PBk30zabWI2KbPcc2mFv5Jk_3YwIgdtrr4S2ReuruFRMpJXyK_KRatnADkjkzawse9FXiN-4"}}