{"@context":["https://www.w3.org/ns/did/v1","https://w3id.org/security/suites/jws-2020/v1"],"id":"did:web:tng-cdn.who.int:v2:trustlist-ref:DCC:ISL:DSC","controller":"did:web:tng-cdn.who.int:v2:trustlist-ref:DCC:ISL","verificationMethod":["did:web:tng-cdn.who.int:v2:trustlist:DCC:ISL:DSC"],"proof":{"type":"JsonWebSignature2020","created":"2025-09-06T06:00:52Z","nonce":"1fd9IHUur8B8RdwvPsPPe39zzof0U9if","proofPurpose":"assertionMethod","verificationMethod":"did:web:raw.githubusercontent.com:WorldHealthOrganization:tng-participants-prod:main:WHO:signing:DID","jws":"eyJiNjQiOmZhbHNlLCJjcml0IjpbImI2NCJdLCJhbGciOiJFUzI1NiJ9..MEUCIQDF73Qk2kB6-wq_yfkl9u5bnzzmYb0LIDSQN4VuMcN40wIgZ_mIsVdnLndAAVWGFOhPWYt7c6ebPUI9MPZEftHW9iI"}}