{"@context":["https://www.w3.org/ns/did/v1","https://w3id.org/security/suites/jws-2020/v1"],"id":"did:web:tng-cdn.who.int:v2:trustlist-ref:DCC:AND:DSC","controller":"did:web:tng-cdn.who.int:v2:trustlist-ref:DCC:AND","verificationMethod":["did:web:tng-cdn.who.int:v2:trustlist:DCC:AND:DSC"],"proof":{"type":"JsonWebSignature2020","created":"2025-08-09T06:00:35Z","nonce":"2IWHgy8qFx0VGbIvPoYVzZTBcWd6w1bp","proofPurpose":"assertionMethod","verificationMethod":"did:web:raw.githubusercontent.com:WorldHealthOrganization:tng-participants-prod:main:WHO:signing:DID","jws":"eyJiNjQiOmZhbHNlLCJjcml0IjpbImI2NCJdLCJhbGciOiJFUzI1NiJ9..MEUCIQDXArDSPGwhoEarSKjeRoZDQxYTN8WwOg7aEtsfhIWSUAIgN3WOU0uG2DjbQJPmne_OJywz7fwkWMsJGPZI-MU0zAw"}}