{"@context":["https://www.w3.org/ns/did/v1","https://w3id.org/security/suites/jws-2020/v1"],"id":"did:web:tng-cdn.who.int:v2:trustlist-ref:-:SVK","controller":"did:web:tng-cdn.who.int:v2:trustlist-ref:-","verificationMethod":["did:web:tng-cdn.who.int:v2:trustlist-ref:-:SVK:SCA"],"proof":{"type":"JsonWebSignature2020","created":"2025-08-09T06:00:35Z","nonce":"Hm1tqoG7pGttERfWaBevWU6QSawzF02s","proofPurpose":"assertionMethod","verificationMethod":"did:web:raw.githubusercontent.com:WorldHealthOrganization:tng-participants-prod:main:WHO:signing:DID","jws":"eyJiNjQiOmZhbHNlLCJjcml0IjpbImI2NCJdLCJhbGciOiJFUzI1NiJ9..MEYCIQDYAl6zD_QFnjtEsRiWMDBfYSZz_9CVnZp1KKsJjV7UPAIhAMMnH7rb-7UDi8SSjnJO6-RIeTRwU3M3MAQgwFr5UFRr"}}