{"@context":["https://www.w3.org/ns/did/v1","https://w3id.org/security/suites/jws-2020/v1"],"id":"did:web:tng-cdn.who.int:v2:trustlist-ref:-:SVN:SCA","controller":"did:web:tng-cdn.who.int:v2:trustlist-ref:-:SVN","verificationMethod":["did:web:tng-cdn.who.int:v2:trustlist:-:SVN:SCA"],"proof":{"type":"JsonWebSignature2020","created":"2025-08-25T06:00:37Z","nonce":"oVqdRd0TaPiHLvei9KqELxDvTFgDi990","proofPurpose":"assertionMethod","verificationMethod":"did:web:raw.githubusercontent.com:WorldHealthOrganization:tng-participants-prod:main:WHO:signing:DID","jws":"eyJiNjQiOmZhbHNlLCJjcml0IjpbImI2NCJdLCJhbGciOiJFUzI1NiJ9..MEYCIQDM_vsb5bRa-xI1Va-i9ciZFt2l_j3OY71FezUhqVIXQAIhAJ8jXMVVc-uXsbxo7j8MDtwNknwQSf26tpUuUR2n_gBZ"}}