{"@context":["https://www.w3.org/ns/did/v1","https://w3id.org/security/suites/jws-2020/v1"],"id":"did:web:tng-cdn.who.int:v2:trustlist-ref:DCC:BEN:DSC","controller":"did:web:tng-cdn.who.int:v2:trustlist-ref:DCC:BEN","verificationMethod":["did:web:tng-cdn.who.int:v2:trustlist:DCC:BEN:DSC"],"proof":{"type":"JsonWebSignature2020","created":"2025-07-12T18:01:02Z","nonce":"cN0frN0lm46JgfY75s6EVpInwEU1CiTV","proofPurpose":"assertionMethod","verificationMethod":"did:web:raw.githubusercontent.com:WorldHealthOrganization:tng-participants-prod:main:WHO:signing:DID","jws":"eyJiNjQiOmZhbHNlLCJjcml0IjpbImI2NCJdLCJhbGciOiJFUzI1NiJ9..MEUCIQDwPSo9D9_4AKQ7B-8HTR6u4Sf_PHjJad3AKyE8wQFoOAIgGV3u40C7WtvRTlSfv1bxoy6kH4nW-aiXBOZ6HmgKZws"}}