{"@context":["https://www.w3.org/ns/did/v1","https://w3id.org/security/suites/jws-2020/v1"],"id":"did:web:tng-cdn.who.int:v2:trustlist-ref:DCC:ISL","controller":"did:web:tng-cdn.who.int:v2:trustlist-ref:DCC","verificationMethod":["did:web:tng-cdn.who.int:v2:trustlist-ref:DCC:ISL:SCA","did:web:tng-cdn.who.int:v2:trustlist-ref:DCC:ISL:DSC"],"proof":{"type":"JsonWebSignature2020","created":"2025-09-27T18:01:17Z","nonce":"N1w4X4i5VJR4DDjQXlmSy5lN8LBao9Cc","proofPurpose":"assertionMethod","verificationMethod":"did:web:raw.githubusercontent.com:WorldHealthOrganization:tng-participants-prod:main:WHO:signing:DID","jws":"eyJiNjQiOmZhbHNlLCJjcml0IjpbImI2NCJdLCJhbGciOiJFUzI1NiJ9..MEUCIQCddQLlXEONuSF5KqN_HdHZgP4dO-pHWfgNY5if_7ouHgIgJxK3ZZIzN0UKLa02ABKa6mVXgIlg0AH37TJPtlThMmY"}}