{"@context":["https://www.w3.org/ns/did/v1","https://w3id.org/security/suites/jws-2020/v1"],"id":"did:web:tng-cdn.who.int:v2:trustlist-ref:DCC:ESP","controller":"did:web:tng-cdn.who.int:v2:trustlist-ref:DCC","verificationMethod":["did:web:tng-cdn.who.int:v2:trustlist-ref:DCC:ESP:SCA","did:web:tng-cdn.who.int:v2:trustlist-ref:DCC:ESP:DSC"],"proof":{"type":"JsonWebSignature2020","created":"2025-12-06T18:01:20Z","nonce":"94hg0NOe6gO7xlgV51TIFVnqTn22r2Kc","proofPurpose":"assertionMethod","verificationMethod":"did:web:raw.githubusercontent.com:WorldHealthOrganization:tng-participants-prod:main:WHO:signing:DID","jws":"eyJiNjQiOmZhbHNlLCJjcml0IjpbImI2NCJdLCJhbGciOiJFUzI1NiJ9..MEUCIQDz-nfnLOHseg0iFrk7Vr15VQcV5UxU65oUzp4r1rQEDQIgEU81CFL67mLGtUrrjj6CWe_gDjabBz38qHCQDrFGBxc"}}