{"@context":["https://www.w3.org/ns/did/v1","https://w3id.org/security/suites/jws-2020/v1"],"id":"did:web:tng-cdn.who.int:v2:trustlist-ref:-:PRT:SCA","controller":"did:web:tng-cdn.who.int:v2:trustlist-ref:-:PRT","verificationMethod":["did:web:tng-cdn.who.int:v2:trustlist:-:PRT:SCA"],"proof":{"type":"JsonWebSignature2020","created":"2025-10-11T18:00:37Z","nonce":"2AyqbMWwNwA6onb5aJ5rPisu9pB6Argg","proofPurpose":"assertionMethod","verificationMethod":"did:web:raw.githubusercontent.com:WorldHealthOrganization:tng-participants-prod:main:WHO:signing:DID","jws":"eyJiNjQiOmZhbHNlLCJjcml0IjpbImI2NCJdLCJhbGciOiJFUzI1NiJ9..MEQCICtZMbwFfbObfabp9w7V234lzU-EhRdkhwzf5VkbZOdZAiBxzSjxT7N8GHYz4EZrAUgcfT84MikKW6WmgyAaR5c7xA"}}