{"@context":["https://www.w3.org/ns/did/v1","https://w3id.org/security/suites/jws-2020/v1"],"id":"did:web:tng-cdn.who.int:v2:trustlist-ref:DCC:BRA","controller":"did:web:tng-cdn.who.int:v2:trustlist-ref:DCC","verificationMethod":["did:web:tng-cdn.who.int:v2:trustlist-ref:DCC:BRA:SCA","did:web:tng-cdn.who.int:v2:trustlist-ref:DCC:BRA:DSC"],"proof":{"type":"JsonWebSignature2020","created":"2025-06-21T18:01:30Z","nonce":"PTlt4Q8ooUtFzJBh6ijBQppK9vsAXw0x","proofPurpose":"assertionMethod","verificationMethod":"did:web:raw.githubusercontent.com:WorldHealthOrganization:tng-participants-prod:main:WHO:signing:DID","jws":"eyJiNjQiOmZhbHNlLCJjcml0IjpbImI2NCJdLCJhbGciOiJFUzI1NiJ9..MEYCIQCIgyzEkv_B2Go80slVf-v115QfOWOdLKS8riSdd7DrDwIhAKP7M3rX_GX5hsOMuNH7T9KTyJvwEaJoW8eFt_OSmwiJ"}}