{"@context":["https://www.w3.org/ns/did/v1","https://w3id.org/security/suites/jws-2020/v1"],"id":"did:web:tng-cdn.who.int:v2:trustlist-ref:DCC:PRT:SCA","controller":"did:web:tng-cdn.who.int:v2:trustlist-ref:DCC:PRT","verificationMethod":["did:web:tng-cdn.who.int:v2:trustlist:DCC:PRT:SCA"],"proof":{"type":"JsonWebSignature2020","created":"2025-09-20T18:00:36Z","nonce":"7G66TdowgO4KgUZa2v5DwV2fChk53FA8","proofPurpose":"assertionMethod","verificationMethod":"did:web:raw.githubusercontent.com:WorldHealthOrganization:tng-participants-prod:main:WHO:signing:DID","jws":"eyJiNjQiOmZhbHNlLCJjcml0IjpbImI2NCJdLCJhbGciOiJFUzI1NiJ9..MEYCIQC76hR4b15VmM1eKKMWTpgerOtjHYLWlVRapN9NGRVTMAIhAMfKuAv-1zyNo4lovwK0EvP-lGKN8lt9DzstS5qFH4Jl"}}