{"@context":["https://www.w3.org/ns/did/v1","https://w3id.org/security/suites/jws-2020/v1"],"id":"did:web:tng-cdn.who.int:v2:trustlist-ref:-:MLT:SCA","controller":"did:web:tng-cdn.who.int:v2:trustlist-ref:-:MLT","verificationMethod":["did:web:tng-cdn.who.int:v2:trustlist:-:MLT:SCA"],"proof":{"type":"JsonWebSignature2020","created":"2025-05-22T00:01:35Z","nonce":"IgEZlXTVaMer2Q8ZSFm41V2E7q7XYDE1","proofPurpose":"assertionMethod","verificationMethod":"did:web:raw.githubusercontent.com:WorldHealthOrganization:tng-participants-prod:main:WHO:signing:DID","jws":"eyJiNjQiOmZhbHNlLCJjcml0IjpbImI2NCJdLCJhbGciOiJFUzI1NiJ9..MEYCIQDHRTcGkdXMaFy5Y7VzVJ9f6GTxD4My1TFxMKXfn54XHgIhANBpHfg5sNIO4Zyex0zqtzQ-7zcR4tG6MaCC2i1KZVoo"}}