{"@context":["https://www.w3.org/ns/did/v1","https://w3id.org/security/suites/jws-2020/v1"],"id":"did:web:tng-cdn.who.int:v2:trustlist-ref:-:MYS","controller":"did:web:tng-cdn.who.int:v2:trustlist-ref:-","verificationMethod":["did:web:tng-cdn.who.int:v2:trustlist-ref:-:MYS:SCA"],"proof":{"type":"JsonWebSignature2020","created":"2025-10-25T18:00:48Z","nonce":"cJ5tK9q3hpnApfFZBaAtDSd2z3RWp0Ng","proofPurpose":"assertionMethod","verificationMethod":"did:web:raw.githubusercontent.com:WorldHealthOrganization:tng-participants-prod:main:WHO:signing:DID","jws":"eyJiNjQiOmZhbHNlLCJjcml0IjpbImI2NCJdLCJhbGciOiJFUzI1NiJ9..MEQCIAfevs9KIic9lEWNkKUTr0jqfJQRby7Cj4CMc4FmM2dRAiAuAKKPbu34Tad0v-2Ev6juenCyrIJZ0rg8VmGzt1YUKw"}}