{"@context":["https://www.w3.org/ns/did/v1","https://w3id.org/security/suites/jws-2020/v1"],"id":"did:web:tng-cdn.who.int:v2:trustlist-ref:DCC:LTU:SCA","controller":"did:web:tng-cdn.who.int:v2:trustlist-ref:DCC:LTU","verificationMethod":["did:web:tng-cdn.who.int:v2:trustlist:DCC:LTU:SCA"],"proof":{"type":"JsonWebSignature2020","created":"2025-05-17T18:01:02Z","nonce":"cQzCVJ7x7GFwzw3l50ID5UQut8ZRNxK8","proofPurpose":"assertionMethod","verificationMethod":"did:web:raw.githubusercontent.com:WorldHealthOrganization:tng-participants-prod:main:WHO:signing:DID","jws":"eyJiNjQiOmZhbHNlLCJjcml0IjpbImI2NCJdLCJhbGciOiJFUzI1NiJ9..MEYCIQDkplAuSCW_8DsqU2XQTcFab8E6ff0_yKdnJe4672VNgAIhANbtbTskhn5YqOt_2LE-MIdNQI53UwMoibWs4f-9DgnI"}}