{"@context":["https://www.w3.org/ns/did/v1","https://w3id.org/security/suites/jws-2020/v1"],"id":"did:web:tng-cdn.who.int:v2:trustlist-ref:DCC:SWE:SCA","controller":"did:web:tng-cdn.who.int:v2:trustlist-ref:DCC:SWE","verificationMethod":["did:web:tng-cdn.who.int:v2:trustlist:DCC:SWE:SCA"],"proof":{"type":"JsonWebSignature2020","created":"2025-08-16T18:00:36Z","nonce":"InHmnOacrhF63kBCEU9dB1TBpZfi1G4u","proofPurpose":"assertionMethod","verificationMethod":"did:web:raw.githubusercontent.com:WorldHealthOrganization:tng-participants-prod:main:WHO:signing:DID","jws":"eyJiNjQiOmZhbHNlLCJjcml0IjpbImI2NCJdLCJhbGciOiJFUzI1NiJ9..MEQCIFocjxV0p6gIIQO2doL_aA6u3BQ-l0N1fPaI0pInJuA7AiBoj8y2M7tAI9pAYJHqX-6FbtSJlrg65Go2Jh-r46pZrQ"}}