{"@context":["https://www.w3.org/ns/did/v1","https://w3id.org/security/suites/jws-2020/v1"],"id":"did:web:tng-cdn.who.int:v2:trustlist-ref:-:THA","controller":"did:web:tng-cdn.who.int:v2:trustlist-ref:-","verificationMethod":["did:web:tng-cdn.who.int:v2:trustlist-ref:-:THA:SCA","did:web:tng-cdn.who.int:v2:trustlist-ref:-:THA:DSC"],"proof":{"type":"JsonWebSignature2020","created":"2025-03-29T18:00:36Z","nonce":"8pUThUvWkkv4PJ6risJusv2lxEWQvNkI","proofPurpose":"assertionMethod","verificationMethod":"did:web:raw.githubusercontent.com:WorldHealthOrganization:tng-participants-prod:main:WHO:signing:DID","jws":"eyJiNjQiOmZhbHNlLCJjcml0IjpbImI2NCJdLCJhbGciOiJFUzI1NiJ9..MEYCIQDOY4v7-6gkwS-gzycHyEnwt7ZoF_XyrmrbRGujOe7yugIhAO741lOzrq6h1D8lgHARfwVaPCqf5dSKJko29tfQcd9F"}}