{"@context":["https://www.w3.org/ns/did/v1","https://w3id.org/security/suites/jws-2020/v1"],"id":"did:web:tng-cdn.who.int:v2:trustlist-ref:-:NZL:SCA","controller":"did:web:tng-cdn.who.int:v2:trustlist-ref:-:NZL","verificationMethod":["did:web:tng-cdn.who.int:v2:trustlist:-:NZL:SCA"],"proof":{"type":"JsonWebSignature2020","created":"2025-05-10T18:01:04Z","nonce":"vsP00KD4XpRixnkM6CH5iPn5Cg1CnZqo","proofPurpose":"assertionMethod","verificationMethod":"did:web:raw.githubusercontent.com:WorldHealthOrganization:tng-participants-prod:main:WHO:signing:DID","jws":"eyJiNjQiOmZhbHNlLCJjcml0IjpbImI2NCJdLCJhbGciOiJFUzI1NiJ9..MEQCIGKOf7pBFDxx1ZM6avt1tmrgg2qHxMd3q6eyTu-0w8MdAiBWPo_w3a3cgqe34bocfifddOCXE9N8rqMmsva3vwoHIA"}}