{"@context":["https://www.w3.org/ns/did/v1","https://w3id.org/security/suites/jws-2020/v1"],"id":"did:web:tng-cdn.who.int:v2:trustlist-ref:-:ARM","controller":"did:web:tng-cdn.who.int:v2:trustlist-ref:-","verificationMethod":["did:web:tng-cdn.who.int:v2:trustlist-ref:-:ARM:SCA","did:web:tng-cdn.who.int:v2:trustlist-ref:-:ARM:DSC"],"proof":{"type":"JsonWebSignature2020","created":"2026-03-01T00:00:36Z","nonce":"Vwa82QCQyUbKn3vefuW8MfMj0i32XjfT","proofPurpose":"assertionMethod","verificationMethod":"did:web:raw.githubusercontent.com:WorldHealthOrganization:tng-participants-prod:main:WHO:signing:DID","jws":"eyJiNjQiOmZhbHNlLCJjcml0IjpbImI2NCJdLCJhbGciOiJFUzI1NiJ9..MEQCIGaCQ4p5CCKQvkFsmtagl-OFyq1ibGsKOwv_0IgQ03C4AiAi0OddTbkMA_ZWqMb5Dq0BtczD580B0O0aumCQD5DUSw"}}