{"@context":["https://www.w3.org/ns/did/v1","https://w3id.org/security/suites/jws-2020/v1"],"id":"did:web:tng-cdn.who.int:v2:trustlist-ref:DCC:SWE","controller":"did:web:tng-cdn.who.int:v2:trustlist-ref:DCC","verificationMethod":["did:web:tng-cdn.who.int:v2:trustlist-ref:DCC:SWE:SCA","did:web:tng-cdn.who.int:v2:trustlist-ref:DCC:SWE:DSC"],"proof":{"type":"JsonWebSignature2020","created":"2025-08-16T18:00:34Z","nonce":"sPwtCKyRjJxYy4wm3YoG6nA32uRd1j9L","proofPurpose":"assertionMethod","verificationMethod":"did:web:raw.githubusercontent.com:WorldHealthOrganization:tng-participants-prod:main:WHO:signing:DID","jws":"eyJiNjQiOmZhbHNlLCJjcml0IjpbImI2NCJdLCJhbGciOiJFUzI1NiJ9..MEQCIH_4ZPo1QbIFzAnUQ6E60uhQPlWWxsNHU5oRRnbvuO2MAiBPuajZ3RgL9JBmik7EPwQ7uH-I8XkDqkywYE7JVcqYiQ"}}