{"@context":["https://www.w3.org/ns/did/v1","https://w3id.org/security/suites/jws-2020/v1"],"id":"did:web:tng-cdn.who.int:v2:trustlist-ref:DCC:SVK","controller":"did:web:tng-cdn.who.int:v2:trustlist-ref:DCC","verificationMethod":["did:web:tng-cdn.who.int:v2:trustlist-ref:DCC:SVK:SCA"],"proof":{"type":"JsonWebSignature2020","created":"2025-11-02T00:00:41Z","nonce":"NAbmoC7yTvwOHaJuT2MmeXt04Wyn4I6j","proofPurpose":"assertionMethod","verificationMethod":"did:web:raw.githubusercontent.com:WorldHealthOrganization:tng-participants-prod:main:WHO:signing:DID","jws":"eyJiNjQiOmZhbHNlLCJjcml0IjpbImI2NCJdLCJhbGciOiJFUzI1NiJ9..MEQCIBIi0OJvcGz3FGXfF8WBkMr75I-84IlCCKYFsxGS5iarAiAUDXUQV5dCgRj9Z9qSM4WXnBbmIlJ1HQlKdv6aoTKmMQ"}}