{"@context":["https://www.w3.org/ns/did/v1","https://w3id.org/security/suites/jws-2020/v1"],"id":"did:web:tng-cdn.who.int:v2:trustlist-ref:DCC:NZL:SCA","controller":"did:web:tng-cdn.who.int:v2:trustlist-ref:DCC:NZL","verificationMethod":["did:web:tng-cdn.who.int:v2:trustlist:DCC:NZL:SCA"],"proof":{"type":"JsonWebSignature2020","created":"2025-09-13T18:00:38Z","nonce":"MwcOytOUbdP23vA98KSish4Wqc7EajcK","proofPurpose":"assertionMethod","verificationMethod":"did:web:raw.githubusercontent.com:WorldHealthOrganization:tng-participants-prod:main:WHO:signing:DID","jws":"eyJiNjQiOmZhbHNlLCJjcml0IjpbImI2NCJdLCJhbGciOiJFUzI1NiJ9..MEUCIAR6041mTVsGoxDTeKBeC4d0MCd0jjaUwWC22eXQmFTWAiEA0DABmwf2Lsp1dfoi0F7nTqirgJKtT-V4uNdq2460uzc"}}