{"@context":["https://www.w3.org/ns/did/v1","https://w3id.org/security/suites/jws-2020/v1"],"id":"did:web:tng-cdn.who.int:v2:trustlist-ref:-:TUR","controller":"did:web:tng-cdn.who.int:v2:trustlist-ref:-","verificationMethod":["did:web:tng-cdn.who.int:v2:trustlist-ref:-:TUR:SCA","did:web:tng-cdn.who.int:v2:trustlist-ref:-:TUR:DSC"],"proof":{"type":"JsonWebSignature2020","created":"2025-03-15T18:00:37Z","nonce":"IQ2puEG6lj952yCBFdZZgX0Wq7vczBDY","proofPurpose":"assertionMethod","verificationMethod":"did:web:raw.githubusercontent.com:WorldHealthOrganization:tng-participants-prod:main:WHO:signing:DID","jws":"eyJiNjQiOmZhbHNlLCJjcml0IjpbImI2NCJdLCJhbGciOiJFUzI1NiJ9..MEUCIGe9TrkazAccFF251RvSV04pyUxz9cQd6rRo6-frc0ePAiEAgTxqPLtZe9ngaP3wvn_Rt9cFbwWto8eDWNYo0kvgXmE"}}