{"@context":["https://www.w3.org/ns/did/v1","https://w3id.org/security/suites/jws-2020/v1"],"id":"did:web:tng-cdn.who.int:v2:trustlist-ref:-:MLT:DSC","controller":"did:web:tng-cdn.who.int:v2:trustlist-ref:-:MLT","verificationMethod":["did:web:tng-cdn.who.int:v2:trustlist:-:MLT:DSC"],"proof":{"type":"JsonWebSignature2020","created":"2026-03-15T00:00:34Z","nonce":"MHqYSuNp356BPfNZIuleV1jPjT58yJJO","proofPurpose":"assertionMethod","verificationMethod":"did:web:raw.githubusercontent.com:WorldHealthOrganization:tng-participants-prod:main:WHO:signing:DID","jws":"eyJiNjQiOmZhbHNlLCJjcml0IjpbImI2NCJdLCJhbGciOiJFUzI1NiJ9..MEUCIEK5QWL06sRQIUaXji_uoLJhebDTXHL0uYYs--vc_3blAiEAq7Lv9XY_o794KOZYnHxrzkl-JI-rXfg4SOGxCHXYx3E"}}