{"@context":["https://www.w3.org/ns/did/v1","https://w3id.org/security/suites/jws-2020/v1"],"id":"did:web:tng-cdn.who.int:v2:trustlist-ref:DCC:BRA:SCA","controller":"did:web:tng-cdn.who.int:v2:trustlist-ref:DCC:BRA","verificationMethod":["did:web:tng-cdn.who.int:v2:trustlist:DCC:BRA:SCA"],"proof":{"type":"JsonWebSignature2020","created":"2025-10-05T00:00:57Z","nonce":"ZxfyVJzeTzXsCKht604FmhxDGHbJHErH","proofPurpose":"assertionMethod","verificationMethod":"did:web:raw.githubusercontent.com:WorldHealthOrganization:tng-participants-prod:main:WHO:signing:DID","jws":"eyJiNjQiOmZhbHNlLCJjcml0IjpbImI2NCJdLCJhbGciOiJFUzI1NiJ9..MEQCICnDuE4629x6V8rU3MDwm_iDLnVN3ufUV5JI65mmOa7wAiALW8C_VglwEp-iudCx5gg8yP2r6QQseBBa0a_ACdfy1g"}}