{"@context":["https://www.w3.org/ns/did/v1","https://w3id.org/security/suites/jws-2020/v1"],"id":"did:web:tng-cdn.who.int:v2:trustlist-ref:DCC:LVA:DSC","controller":"did:web:tng-cdn.who.int:v2:trustlist-ref:DCC:LVA","verificationMethod":["did:web:tng-cdn.who.int:v2:trustlist:DCC:LVA:DSC"],"proof":{"type":"JsonWebSignature2020","created":"2026-02-22T00:00:41Z","nonce":"KPDaRr2ZUE1U25sU0KdpTD02ANC35ARj","proofPurpose":"assertionMethod","verificationMethod":"did:web:raw.githubusercontent.com:WorldHealthOrganization:tng-participants-prod:main:WHO:signing:DID","jws":"eyJiNjQiOmZhbHNlLCJjcml0IjpbImI2NCJdLCJhbGciOiJFUzI1NiJ9..MEYCIQCHYtMlWBYohD2F7zk8VxMl1LHUb57TRihhCkmGRjyCaAIhALjWRAJAk7oFB3MziNW792ErM4EXEyGXlnMC840QQWaH"}}