{"@context":["https://www.w3.org/ns/did/v1","https://w3id.org/security/suites/jws-2020/v1"],"id":"did:web:tng-cdn.who.int:v2:trustlist-ref:-:ESP:DSC","controller":"did:web:tng-cdn.who.int:v2:trustlist-ref:-:ESP","verificationMethod":["did:web:tng-cdn.who.int:v2:trustlist:-:ESP:DSC"],"proof":{"type":"JsonWebSignature2020","created":"2025-07-15T00:01:12Z","nonce":"xDxfJQfR0h2GZYfjn5UsTJ7oNX95Mcn9","proofPurpose":"assertionMethod","verificationMethod":"did:web:raw.githubusercontent.com:WorldHealthOrganization:tng-participants-prod:main:WHO:signing:DID","jws":"eyJiNjQiOmZhbHNlLCJjcml0IjpbImI2NCJdLCJhbGciOiJFUzI1NiJ9..MEUCIQCZ0lQ6hQRux5gF4SrfWUdo0O-qG99UG25nYx3_L_NzHgIgeDoR7VaZOWGWSSEw9wCWQJkQ4fmbPtiSO7D7QO8EHnQ"}}