{"@context":["https://www.w3.org/ns/did/v1","https://w3id.org/security/suites/jws-2020/v1"],"id":"did:web:tng-cdn.who.int:v2:trustlist-ref:-:ESP:DSC","controller":"did:web:tng-cdn.who.int:v2:trustlist-ref:-:ESP","verificationMethod":["did:web:tng-cdn.who.int:v2:trustlist:-:ESP:DSC"],"proof":{"type":"JsonWebSignature2020","created":"2025-10-25T18:00:50Z","nonce":"c2cKbyDtDUvIs1TzpCnQRNJjpteeXmDI","proofPurpose":"assertionMethod","verificationMethod":"did:web:raw.githubusercontent.com:WorldHealthOrganization:tng-participants-prod:main:WHO:signing:DID","jws":"eyJiNjQiOmZhbHNlLCJjcml0IjpbImI2NCJdLCJhbGciOiJFUzI1NiJ9..MEQCIDkpmu1gzLGAIeviE39F9ibRQa8CFehD9wjW_ozVtMnYAiBTLJ6hU0abKyIB06nggaFBof8HSQQbLFG7w6UdkUCYZA"}}