{"@context":["https://www.w3.org/ns/did/v1","https://w3id.org/security/suites/jws-2020/v1"],"id":"did:web:tng-cdn.who.int:v2:trustlist-ref:-:CYP:DSC","controller":"did:web:tng-cdn.who.int:v2:trustlist-ref:-:CYP","verificationMethod":["did:web:tng-cdn.who.int:v2:trustlist:-:CYP:DSC"],"proof":{"type":"JsonWebSignature2020","created":"2025-03-15T18:00:38Z","nonce":"YorzIJ3Qrdqw7nUvnpsdiJEkcUB8t1XW","proofPurpose":"assertionMethod","verificationMethod":"did:web:raw.githubusercontent.com:WorldHealthOrganization:tng-participants-prod:main:WHO:signing:DID","jws":"eyJiNjQiOmZhbHNlLCJjcml0IjpbImI2NCJdLCJhbGciOiJFUzI1NiJ9..MEQCHxepHFeEEEeXN2nwXeEL2cEEF5QFulmYd4VmHd4LZXcCIQD3O7npZ3Q_TW3qpmTPOJEhKYH5qM3BzSHIFfx2sHHL2A"}}